startupthreads/__init__.py
startupthreads/__main__.py
startupthreads/swag.py
startupthreads_cli-0.1.14.dist-info/DESCRIPTION.rst
startupthreads_cli-0.1.14.dist-info/entry_points.txt
startupthreads_cli-0.1.14.dist-info/METADATA
startupthreads_cli-0.1.14.dist-info/metadata.json
startupthreads_cli-0.1.14.dist-info/RECORD
startupthreads_cli-0.1.14.dist-info/top_level.txt
startupthreads_cli-0.1.14.dist-info/WHEEL
