Metadata-Version: 2.0
Name: startupthreads-cli
Version: 0.1.14
Summary: Startup Threads CLI
Home-page: https://github.com/soulshake/startup-threads-cli
Author: AJ Bowen
Author-email: aj@gandi.net
License: MIT
Keywords: startup threads startupthreads cli swag shirts
Platform: UNKNOWN
Requires-Dist: click (==3.3)
Requires-Dist: arrow (==0.5.4)
Requires-Dist: requests (==2.7.0)
Requires-Dist: tabulate (==0.7.5)
